{
  "pdf_title": "Kenya Gazette Vol CXINo 107",
  "pdf_file_name": "Kenya Gazette Vol CXINo 107.pdf",
  "pdf_path": "C:\\Users\\Ronald Wahome\\Documents\\docling_spatial_pdfs\\pdfs\\Kenya Gazette Vol CXINo 107.pdf",
  "pdf_size_bytes": 103483,
  "pages": 2,
  "docling": {
    "export_summary": {
      "schema_name": "DoclingDocument",
      "version": "1.10.0",
      "name": "Kenya Gazette Vol CXINo 107",
      "texts_count": 61,
      "tables_count": 0,
      "pictures_count": 1,
      "pages_count": null
    },
    "full_markdown": "## SPECIAL ISSUE\n\n<!-- image -->\n\n## THE KENYA\n\nPublished by Authority of the Republic of Kenya\n\n(Registered as a Newspaper at the G.P.O.)\n\n## NAIROBI, 18th December, 2009  \t Price Sh. 50\n\nVol. CXI----No. 107\n\n## GAZETTE NOTICE NO. 13809\n\nBUSINESS PROCESS OUTSOURCING /INFORMATION TECHNOLOGY SERVICES (BPO/ff ES) WORKING GROUP\n\n## APPOINTMENT\n\nIN EXERCISE of the powers conferred by section  4  (1) (a) of the National Accord and Reconciliation Act, I, Rolla Amolo Odinga, Prime Nnister of the Republic of Kenya appoint-\n\nGilds Odem-Chaiiperson,\n\nNick Nesbit-Member,\n\nPeris Wereykmber/Joint Secretary,\n\nVictor KyotoMember/Joint Secretary,\n\nSammy Buruchara-Member,\n\nSilvester Kasuku-OPM Member/Head of Secretariat,\n\nDickson Ogolla-Secretariat, to be members of the BPO/ITES Working Group, for a period of two (2) years beginning 18th December, 2009.\n\n## Terms of Reference for the Working Group\n\n1. To guide, facilitate and oversee the development of an effective working system on BPO/ITES related activities within the various government ministries that will result in an organized and cohesive co-ordination of efforts towards meeting 'the objectives of Vision 2030 for the BPO/ITES sector.\n2. To Facilitate and oversee the development and achievement of high level interaction and negotiations with domestic, regional and international partners for facilitation of industry growth.\n3. To monitor and advice provision of infrastructure for the BPO/ITES sector through the Office of the Prime Minister.\n4. To oversee the process to actively generate new business and investment in the sector through facilitating \"tent pitching\" of foreign investors by direct one to one meetings with senior level outsourcing decision makers in Global 1000 companies.\n5. To facilitate, co-ordinate and oversee the development of a strategy for Rural BPO/ITES efforts between various ministries towards effecting adequate sector growth in rural/suburban areas so as to\n\nstem rural-urban migration as well as encourage development in smaller towns and rural areas.\n\n6. To guide, facilitate and oversee the development of a monitoring and evaluation framework that will assess the general status on the development of the sector.\n7. To monitor and evaluate the impact of BPO/ITES related activities based on key milestones and objectives.\n\n## Powers of the Working Group\n\n1. The Working Group may establish committees to address technical or other specific issues. The Working C)Irctip will prepare the Terms of Reference of its Committees. The membership of the committees will draw from relevant institutions, particularly: Ministry of Information and Communication, Ministry of Trade, Ministry of Science and Technology and Ministry of Education, Vision 2030 Secretariat, Brand Kenya Board, E-Govemment, ICT Board, Kenya Investment Authority, Export Processing Zones Authority and KEPSA among others.\n2. The , Working Group and its committees may invite external experts to participate on an ad hoc basis in one or more of their meetings.\n\nDated the 16th December, 2009.\n\nGAZETTE NOTICE No. 13810\n\nTHE NATIONAL HOSPITAL INSURANCE FUND ACT (No. 9 of 1998)\n\n## APPOINTMENT\n\nIN EXERCISE of the powers conferred by section 4. of the National Hospital Insurance Fund Act, the Minister for Medical Services appoints-\n\nUnder paragraph (1) (g)-\n\nGeorge Odiko\n\nUnder paragraph (1) (i)-\n\nElijah Adul Onyango ci0 ft's--) 00.1 ' 30,1LOP' cp l ov\n\nR. A. ODINGA,\n\nPrime Minister.\n\n3728\n\nUnder paragraph (1) (I) (I)-\n\nThornas'Matha , pidashi\n\nUnder panigniph (1) (f)iii)\n\nMaul Joshua SUnde (key.)\n\nUnder paragraph (1) (1)-\n\nDavid Lemirdi IConchella to be members of the National Hospital Insurance Pend Board of Management with effect from 19th December, 2009.\n\nDated the 17th December, 2009.\n\nP. A. NYONG'0, MGrirter for Medical Services.\n\nGAZETTE NOTICE No. 13811\n\n## THE KENYA MEDICAL TRAINING COLLEGE ACT\n\n(Cap. 261)\n\nAPPOINTMENT\n\nIN EXERCISE of the powers conferred by section 9 (1) of the Kenya Medical Training College Act, the Minister for Medical Services appoints-\n\nUnder paragraph (1) ()-\n\nDavid Valor Tared&amp; Margaret Anyango Odidi to be members of the Kenya Medical Training College Board of Management with effect from 19th December, 2009.\n\nDated the 17th December, 2009.\n\nP. A. NYONG'O, Minister for Medical Services.",
    "full_plain_text": "SPECIAL ISSUE\n\nTHE KENYA\n\nPublished by Authority of the Republic of Kenya\n\n(Registered as a Newspaper at the G.P.O.)\n\nNAIROBI, 18th December, 2009  \t Price Sh. 50\n\nVol. CXI----No. 107\n\nGAZETTE NOTICE NO. 13809\n\nBUSINESS PROCESS OUTSOURCING /INFORMATION TECHNOLOGY SERVICES (BPO/ff ES) WORKING GROUP\n\nAPPOINTMENT\n\nIN EXERCISE of the powers conferred by section  4  (1) (a) of the National Accord and Reconciliation Act, I, Rolla Amolo Odinga, Prime Nnister of the Republic of Kenya appoint-\n\nGilds Odem-Chaiiperson,\n\nNick Nesbit-Member,\n\nPeris Wereykmber/Joint Secretary,\n\nVictor KyotoMember/Joint Secretary,\n\nSammy Buruchara-Member,\n\nSilvester Kasuku-OPM Member/Head of Secretariat,\n\nDickson Ogolla-Secretariat, to be members of the BPO/ITES Working Group, for a period of two (2) years beginning 18th December, 2009.\n\nTerms of Reference for the Working Group\n\n1. To guide, facilitate and oversee the development of an effective working system on BPO/ITES related activities within the various government ministries that will result in an organized and cohesive co-ordination of efforts towards meeting 'the objectives of Vision 2030 for the BPO/ITES sector.\n2. To Facilitate and oversee the development and achievement of high level interaction and negotiations with domestic, regional and international partners for facilitation of industry growth.\n3. To monitor and advice provision of infrastructure for the BPO/ITES sector through the Office of the Prime Minister.\n4. To oversee the process to actively generate new business and investment in the sector through facilitating \"tent pitching\" of foreign investors by direct one to one meetings with senior level outsourcing decision makers in Global 1000 companies.\n5. To facilitate, co-ordinate and oversee the development of a strategy for Rural BPO/ITES efforts between various ministries towards effecting adequate sector growth in rural/suburban areas so as to\n\nstem rural-urban migration as well as encourage development in smaller towns and rural areas.\n\n6. To guide, facilitate and oversee the development of a monitoring and evaluation framework that will assess the general status on the development of the sector.\n7. To monitor and evaluate the impact of BPO/ITES related activities based on key milestones and objectives.\n\nPowers of the Working Group\n\n1. The Working Group may establish committees to address technical or other specific issues. The Working C)Irctip will prepare the Terms of Reference of its Committees. The membership of the committees will draw from relevant institutions, particularly: Ministry of Information and Communication, Ministry of Trade, Ministry of Science and Technology and Ministry of Education, Vision 2030 Secretariat, Brand Kenya Board, E-Govemment, ICT Board, Kenya Investment Authority, Export Processing Zones Authority and KEPSA among others.\n2. The , Working Group and its committees may invite external experts to participate on an ad hoc basis in one or more of their meetings.\n\nDated the 16th December, 2009.\n\nGAZETTE NOTICE No. 13810\n\nTHE NATIONAL HOSPITAL INSURANCE FUND ACT (No. 9 of 1998)\n\nAPPOINTMENT\n\nIN EXERCISE of the powers conferred by section 4. of the National Hospital Insurance Fund Act, the Minister for Medical Services appoints-\n\nUnder paragraph (1) (g)-\n\nGeorge Odiko\n\nUnder paragraph (1) (i)-\n\nElijah Adul Onyango ci0 ft's--) 00.1 ' 30,1LOP' cp l ov\n\nR. A. ODINGA,\n\nPrime Minister.\n\n3728\n\nUnder paragraph (1) (I) (I)-\n\nThornas'Matha , pidashi\n\nUnder panigniph (1) (f)iii)\n\nMaul Joshua SUnde (key.)\n\nUnder paragraph (1) (1)-\n\nDavid Lemirdi IConchella to be members of the National Hospital Insurance Pend Board of Management with effect from 19th December, 2009.\n\nDated the 17th December, 2009.\n\nP. A. NYONG'0, MGrirter for Medical Services.\n\nGAZETTE NOTICE No. 13811\n\nTHE KENYA MEDICAL TRAINING COLLEGE ACT\n\n(Cap. 261)\n\nAPPOINTMENT\n\nIN EXERCISE of the powers conferred by section 9 (1) of the Kenya Medical Training College Act, the Minister for Medical Services appoints-\n\nUnder paragraph (1) ()-\n\nDavid Valor Tared& Margaret Anyango Odidi to be members of the Kenya Medical Training College Board of Management with effect from 19th December, 2009.\n\nDated the 17th December, 2009.\n\nP. A. NYONG'O, Minister for Medical Services.",
    "full_plain_text_spatial": "SPECIAL ISSUE\n\nTHE KENYA\n\nVol. CXI----No. 107\n\nGAZETTE NOTICE NO. 13809\n\nBUSINESS PROCESS OUTSOURCING /INFORMATION TECHNOLOGY SERVICES (BPO/ff ES) WORKING GROUP\n\nAPPOINTMENT\n\nIN EXERCISE of the powers conferred by section  4  (1) (a) of the National Accord and Reconciliation Act, I, Rolla Amolo Odinga, Prime Nnister of the Republic of Kenya appoint-\n\nGilds Odem-Chaiiperson,\n\nNick Nesbit-Member,\n\nPeris Wereykmber/Joint Secretary,\n\nVictor KyotoMember/Joint Secretary,\n\nSammy Buruchara-Member,\n\nSilvester Kasuku-OPM Member/Head of Secretariat,\n\nDickson Ogolla-Secretariat, to be members of the BPO/ITES Working Group, for a period of two (2) years beginning 18th December, 2009.\n\nTerms of Reference for the Working Group\n\nTo guide, facilitate and oversee the development of an effective working system on BPO/ITES related activities within the various government ministries that will result in an organized and cohesive co-ordination of efforts towards meeting 'the objectives of Vision 2030 for the BPO/ITES sector.\n\nTo Facilitate and oversee the development and achievement of high level interaction and negotiations with domestic, regional and international partners for facilitation of industry growth.\n\nTo monitor and advice provision of infrastructure for the BPO/ITES sector through the Office of the Prime Minister.\n\nTo oversee the process to actively generate new business and investment in the sector through facilitating \"tent pitching\" of foreign investors by direct one to one meetings with senior level outsourcing decision makers in Global 1000 companies.\n\nTo facilitate, co-ordinate and oversee the development of a strategy for Rural BPO/ITES efforts between various ministries towards effecting adequate sector growth in rural/suburban areas so as to\n\nPublished by Authority of the Republic of Kenya\n\nstem rural-urban migration as well as encourage development in smaller towns and rural areas.\n\nTo guide, facilitate and oversee the development of a monitoring and evaluation framework that will assess the general status on the development of the sector.\n\nTo monitor and evaluate the impact of BPO/ITES related activities based on key milestones and objectives.\n\nPowers of the Working Group\n\nThe Working Group may establish committees to address technical or other specific issues. The Working C)Irctip will prepare the Terms of Reference of its Committees. The membership of the committees will draw from relevant institutions, particularly: Ministry of Information and Communication, Ministry of Trade, Ministry of Science and Technology and Ministry of Education, Vision 2030 Secretariat, Brand Kenya Board, E-Govemment, ICT Board, Kenya Investment Authority, Export Processing Zones Authority and KEPSA among others.\n\nThe , Working Group and its committees may invite external experts to participate on an ad hoc basis in one or more of their meetings.\n\nDated the 16th December, 2009.\n\nR. A. ODINGA,\n\nPrime Minister.\n\nGAZETTE NOTICE No. 13810\n\nTHE NATIONAL HOSPITAL INSURANCE FUND ACT (No. 9 of 1998)\n\nAPPOINTMENT\n\nIN EXERCISE of the powers conferred by section 4. of the National Hospital Insurance Fund Act, the Minister for Medical Services appoints-\n\nUnder paragraph (1) (g)-\n\nGeorge Odiko\n\nUnder paragraph (1) (i)-\n\nElijah Adul Onyango ci0 ft's--) 00.1 ' 30,1LOP' cp l ov\n\n(Registered as a Newspaper at the G.P.O.)\n\nNAIROBI, 18th December, 2009  \t Price Sh. 50\n\n3728\n\nUnder paragraph (1) (I) (I)-\n\nThornas'Matha , pidashi\n\nUnder panigniph (1) (f)iii)\n\nMaul Joshua SUnde (key.)\n\nUnder paragraph (1) (1)-\n\nDavid Lemirdi IConchella to be members of the National Hospital Insurance Pend Board of Management with effect from 19th December, 2009.\n\nDated the 17th December, 2009.\n\nP. A. NYONG'0, MGrirter for Medical Services.\n\nTHE KENYA MEDICAL TRAINING COLLEGE ACT\n\n(Cap. 261)\n\nAPPOINTMENT\n\nIN EXERCISE of the powers conferred by section 9 (1) of the Kenya Medical Training College Act, the Minister for Medical Services appoints-\n\nUnder paragraph (1) ()-\n\nDavid Valor Tared& Margaret Anyango Odidi to be members of the Kenya Medical Training College Board of Management with effect from 19th December, 2009.\n\nDated the 17th December, 2009.\n\nP. A. NYONG'O, Minister for Medical Services.\n\nGAZETTE NOTICE No. 13811"
  },
  "corrigenda": [],
  "gazette_notices": [
    {
      "gazette_notice_no": "13809",
      "gazette_notice_header": "GAZETTE NOTICE NO. 13809",
      "title_lines": [
        "BUSINESS PROCESS OUTSOURCING /INFORMATION TECHNOLOGY SERVICES (BPO/ff ES) WORKING GROUP"
      ],
      "gazette_notice_full_text": "GAZETTE NOTICE NO. 13809\nBUSINESS PROCESS OUTSOURCING /INFORMATION TECHNOLOGY SERVICES (BPO/ff ES) WORKING GROUP\n\nAPPOINTMENT\n\nIN EXERCISE of the powers conferred by section  4  (1) (a) of the National Accord and Reconciliation Act, I, Rolla Amolo Odinga, Prime Nnister of the Republic of Kenya appoint-\n\nGilds Odem-Chaiiperson,\n\nNick Nesbit-Member,\n\nPeris Wereykmber/Joint Secretary,\n\nVictor KyotoMember/Joint Secretary,\n\nSammy Buruchara-Member,\n\nSilvester Kasuku-OPM Member/Head of Secretariat,\n\nDickson Ogolla-Secretariat, to be members of the BPO/ITES Working Group, for a period of two (2) years beginning 18th December, 2009.\n\nTerms of Reference for the Working Group\n\nTo guide, facilitate and oversee the development of an effective working system on BPO/ITES related activities within the various government ministries that will result in an organized and cohesive co-ordination of efforts towards meeting 'the objectives of Vision 2030 for the BPO/ITES sector.\n\nTo Facilitate and oversee the development and achievement of high level interaction and negotiations with domestic, regional and international partners for facilitation of industry growth.\n\nTo monitor and advice provision of infrastructure for the BPO/ITES sector through the Office of the Prime Minister.\n\nTo oversee the process to actively generate new business and investment in the sector through facilitating \"tent pitching\" of foreign investors by direct one to one meetings with senior level outsourcing decision makers in Global 1000 companies.\n\nTo facilitate, co-ordinate and oversee the development of a strategy for Rural BPO/ITES efforts between various ministries towards effecting adequate sector growth in rural/suburban areas so as to\n\nPublished by Authority of the Republic of Kenya\n\nstem rural-urban migration as well as encourage development in smaller towns and rural areas.\n\nTo guide, facilitate and oversee the development of a monitoring and evaluation framework that will assess the general status on the development of the sector.\n\nTo monitor and evaluate the impact of BPO/ITES related activities based on key milestones and objectives.\n\nPowers of the Working Group\n\nThe Working Group may establish committees to address technical or other specific issues. The Working C)Irctip will prepare the Terms of Reference of its Committees. The membership of the committees will draw from relevant institutions, particularly: Ministry of Information and Communication, Ministry of Trade, Ministry of Science and Technology and Ministry of Education, Vision 2030 Secretariat, Brand Kenya Board, E-Govemment, ICT Board, Kenya Investment Authority, Export Processing Zones Authority and KEPSA among others.\n\nThe , Working Group and its committees may invite external experts to participate on an ad hoc basis in one or more of their meetings.\n\nDated the 16th December, 2009.\n\nR. A. ODINGA,\n\nPrime Minister.\n\nGAZETTE NOTICE No. 13810\n\nTHE NATIONAL HOSPITAL INSURANCE FUND ACT (No. 9 of 1998)\n\nAPPOINTMENT\n\nIN EXERCISE of the powers conferred by section 4. of the National Hospital Insurance Fund Act, the Minister for Medical Services appoints-\n\nUnder paragraph (1) (g)-\n\nGeorge Odiko\n\nUnder paragraph (1) (i)-\n\nElijah Adul Onyango ci0 ft's--) 00.1 ' 30,1LOP' cp l ov\n\n(Registered as a Newspaper at the G.P.O.)\n\nNAIROBI, 18th December, 2009  \t Price Sh. 50\n\n\nUnder paragraph (1) (I) (I)-\n\nThornas'Matha , pidashi\n\nUnder panigniph (1) (f)iii)\n\nMaul Joshua SUnde (key.)\n\nUnder paragraph (1) (1)-\n\nDavid Lemirdi IConchella to be members of the National Hospital Insurance Pend Board of Management with effect from 19th December, 2009.\n\nDated the 17th December, 2009.\n\nP. A. NYONG'0, MGrirter for Medical Services.\n\nTHE KENYA MEDICAL TRAINING COLLEGE ACT\n\n(Cap. 261)\n\nAPPOINTMENT\n\nIN EXERCISE of the powers conferred by section 9 (1) of the Kenya Medical Training College Act, the Minister for Medical Services appoints-\n\nUnder paragraph (1) ()-\n\nDavid Valor Tared& Margaret Anyango Odidi to be members of the Kenya Medical Training College Board of Management with effect from 19th December, 2009.\n\nDated the 17th December, 2009.\n\nP. A. NYONG'O, Minister for Medical Services.\n\nGAZETTE NOTICE No. 13811",
      "body_segments": [
        {
          "type": "text",
          "lines": [
            "APPOINTMENT"
          ]
        },
        {
          "type": "blank",
          "line": ""
        },
        {
          "type": "text",
          "lines": [
            "IN EXERCISE of the powers conferred by section  4  (1) (a) of the National Accord and Reconciliation Act, I, Rolla Amolo Odinga, Prime Nnister of the Republic of Kenya appoint-"
          ]
        },
        {
          "type": "blank",
          "line": ""
        },
        {
          "type": "text",
          "lines": [
            "Gilds Odem-Chaiiperson,"
          ]
        },
        {
          "type": "blank",
          "line": ""
        },
        {
          "type": "text",
          "lines": [
            "Nick Nesbit-Member,"
          ]
        },
        {
          "type": "blank",
          "line": ""
        },
        {
          "type": "text",
          "lines": [
            "Peris Wereykmber/Joint Secretary,"
          ]
        },
        {
          "type": "blank",
          "line": ""
        },
        {
          "type": "text",
          "lines": [
            "Victor KyotoMember/Joint Secretary,"
          ]
        },
        {
          "type": "blank",
          "line": ""
        },
        {
          "type": "text",
          "lines": [
            "Sammy Buruchara-Member,"
          ]
        },
        {
          "type": "blank",
          "line": ""
        },
        {
          "type": "text",
          "lines": [
            "Silvester Kasuku-OPM Member/Head of Secretariat,"
          ]
        },
        {
          "type": "blank",
          "line": ""
        },
        {
          "type": "text",
          "lines": [
            "Dickson Ogolla-Secretariat, to be members of the BPO/ITES Working Group, for a period of two (2) years beginning 18th December, 2009."
          ]
        },
        {
          "type": "blank",
          "line": ""
        },
        {
          "type": "text",
          "lines": [
            "Terms of Reference for the Working Group"
          ]
        },
        {
          "type": "blank",
          "line": ""
        },
        {
          "type": "text",
          "lines": [
            "To guide, facilitate and oversee the development of an effective working system on BPO/ITES related activities within the various government ministries that will result in an organized and cohesive co-ordination of efforts towards meeting 'the objectives of Vision 2030 for the BPO/ITES sector."
          ]
        },
        {
          "type": "blank",
          "line": ""
        },
        {
          "type": "text",
          "lines": [
            "To Facilitate and oversee the development and achievement of high level interaction and negotiations with domestic, regional and international partners for facilitation of industry growth."
          ]
        },
        {
          "type": "blank",
          "line": ""
        },
        {
          "type": "text",
          "lines": [
            "To monitor and advice provision of infrastructure for the BPO/ITES sector through the Office of the Prime Minister."
          ]
        },
        {
          "type": "blank",
          "line": ""
        },
        {
          "type": "text",
          "lines": [
            "To oversee the process to actively generate new business and investment in the sector through facilitating \"tent pitching\" of foreign investors by direct one to one meetings with senior level outsourcing decision makers in Global 1000 companies."
          ]
        },
        {
          "type": "blank",
          "line": ""
        },
        {
          "type": "text",
          "lines": [
            "To facilitate, co-ordinate and oversee the development of a strategy for Rural BPO/ITES efforts between various ministries towards effecting adequate sector growth in rural/suburban areas so as to"
          ]
        },
        {
          "type": "blank",
          "line": ""
        },
        {
          "type": "text",
          "lines": [
            "Published by Authority of the Republic of Kenya"
          ]
        },
        {
          "type": "blank",
          "line": ""
        },
        {
          "type": "text",
          "lines": [
            "stem rural-urban migration as well as encourage development in smaller towns and rural areas."
          ]
        },
        {
          "type": "blank",
          "line": ""
        },
        {
          "type": "text",
          "lines": [
            "To guide, facilitate and oversee the development of a monitoring and evaluation framework that will assess the general status on the development of the sector."
          ]
        },
        {
          "type": "blank",
          "line": ""
        },
        {
          "type": "text",
          "lines": [
            "To monitor and evaluate the impact of BPO/ITES related activities based on key milestones and objectives."
          ]
        },
        {
          "type": "blank",
          "line": ""
        },
        {
          "type": "text",
          "lines": [
            "Powers of the Working Group"
          ]
        },
        {
          "type": "blank",
          "line": ""
        },
        {
          "type": "text",
          "lines": [
            "The Working Group may establish committees to address technical or other specific issues. The Working C)Irctip will prepare the Terms of Reference of its Committees. The membership of the committees will draw from relevant institutions, particularly: Ministry of Information and Communication, Ministry of Trade, Ministry of Science and Technology and Ministry of Education, Vision 2030 Secretariat, Brand Kenya Board, E-Govemment, ICT Board, Kenya Investment Authority, Export Processing Zones Authority and KEPSA among others."
          ]
        },
        {
          "type": "blank",
          "line": ""
        },
        {
          "type": "text",
          "lines": [
            "The , Working Group and its committees may invite external experts to participate on an ad hoc basis in one or more of their meetings."
          ]
        },
        {
          "type": "blank",
          "line": ""
        },
        {
          "type": "text",
          "lines": [
            "Dated the 16th December, 2009."
          ]
        },
        {
          "type": "blank",
          "line": ""
        },
        {
          "type": "text",
          "lines": [
            "R. A. ODINGA,"
          ]
        },
        {
          "type": "blank",
          "line": ""
        },
        {
          "type": "text",
          "lines": [
            "Prime Minister."
          ]
        },
        {
          "type": "blank",
          "line": ""
        },
        {
          "type": "text",
          "lines": [
            "GAZETTE NOTICE No. 13810"
          ]
        },
        {
          "type": "blank",
          "line": ""
        },
        {
          "type": "text",
          "lines": [
            "THE NATIONAL HOSPITAL INSURANCE FUND ACT (No. 9 of 1998)"
          ]
        },
        {
          "type": "blank",
          "line": ""
        },
        {
          "type": "text",
          "lines": [
            "APPOINTMENT"
          ]
        },
        {
          "type": "blank",
          "line": ""
        },
        {
          "type": "text",
          "lines": [
            "IN EXERCISE of the powers conferred by section 4. of the National Hospital Insurance Fund Act, the Minister for Medical Services appoints-"
          ]
        },
        {
          "type": "blank",
          "line": ""
        },
        {
          "type": "text",
          "lines": [
            "Under paragraph (1) (g)-"
          ]
        },
        {
          "type": "blank",
          "line": ""
        },
        {
          "type": "text",
          "lines": [
            "George Odiko"
          ]
        },
        {
          "type": "blank",
          "line": ""
        },
        {
          "type": "text",
          "lines": [
            "Under paragraph (1) (i)-"
          ]
        },
        {
          "type": "blank",
          "line": ""
        },
        {
          "type": "text",
          "lines": [
            "Elijah Adul Onyango ci0 ft's--) 00.1 ' 30,1LOP' cp l ov"
          ]
        },
        {
          "type": "blank",
          "line": ""
        },
        {
          "type": "text",
          "lines": [
            "(Registered as a Newspaper at the G.P.O.)"
          ]
        },
        {
          "type": "blank",
          "line": ""
        },
        {
          "type": "text",
          "lines": [
            "NAIROBI, 18th December, 2009  \t Price Sh. 50"
          ]
        },
        {
          "type": "blank",
          "line": ""
        },
        {
          "type": "blank",
          "line": ""
        },
        {
          "type": "text",
          "lines": [
            "Under paragraph (1) (I) (I)-"
          ]
        },
        {
          "type": "blank",
          "line": ""
        },
        {
          "type": "text",
          "lines": [
            "Thornas'Matha , pidashi"
          ]
        },
        {
          "type": "blank",
          "line": ""
        },
        {
          "type": "text",
          "lines": [
            "Under panigniph (1) (f)iii)"
          ]
        },
        {
          "type": "blank",
          "line": ""
        },
        {
          "type": "text",
          "lines": [
            "Maul Joshua SUnde (key.)"
          ]
        },
        {
          "type": "blank",
          "line": ""
        },
        {
          "type": "text",
          "lines": [
            "Under paragraph (1) (1)-"
          ]
        },
        {
          "type": "blank",
          "line": ""
        },
        {
          "type": "text",
          "lines": [
            "David Lemirdi IConchella to be members of the National Hospital Insurance Pend Board of Management with effect from 19th December, 2009."
          ]
        },
        {
          "type": "blank",
          "line": ""
        },
        {
          "type": "text",
          "lines": [
            "Dated the 17th December, 2009."
          ]
        },
        {
          "type": "blank",
          "line": ""
        },
        {
          "type": "text",
          "lines": [
            "P. A. NYONG'0, MGrirter for Medical Services."
          ]
        },
        {
          "type": "blank",
          "line": ""
        },
        {
          "type": "text",
          "lines": [
            "THE KENYA MEDICAL TRAINING COLLEGE ACT"
          ]
        },
        {
          "type": "blank",
          "line": ""
        },
        {
          "type": "text",
          "lines": [
            "(Cap. 261)"
          ]
        },
        {
          "type": "blank",
          "line": ""
        },
        {
          "type": "text",
          "lines": [
            "APPOINTMENT"
          ]
        },
        {
          "type": "blank",
          "line": ""
        },
        {
          "type": "text",
          "lines": [
            "IN EXERCISE of the powers conferred by section 9 (1) of the Kenya Medical Training College Act, the Minister for Medical Services appoints-"
          ]
        },
        {
          "type": "blank",
          "line": ""
        },
        {
          "type": "text",
          "lines": [
            "Under paragraph (1) ()-"
          ]
        },
        {
          "type": "blank",
          "line": ""
        },
        {
          "type": "text",
          "lines": [
            "David Valor Tared& Margaret Anyango Odidi to be members of the Kenya Medical Training College Board of Management with effect from 19th December, 2009."
          ]
        },
        {
          "type": "blank",
          "line": ""
        },
        {
          "type": "text",
          "lines": [
            "Dated the 17th December, 2009."
          ]
        },
        {
          "type": "blank",
          "line": ""
        },
        {
          "type": "text",
          "lines": [
            "P. A. NYONG'O, Minister for Medical Services."
          ]
        },
        {
          "type": "blank",
          "line": ""
        },
        {
          "type": "text",
          "lines": [
            "GAZETTE NOTICE No. 13811"
          ]
        }
      ],
      "other_attributes": {
        "char_span_start_line": 6,
        "char_span_end_line": 115,
        "lines_in_body": 107
      }
    }
  ]
}